changelog/.gitempty
dkist_processing_pac/__init__.py
dkist_processing_pac/data/__init__.py
dkist_processing_pac/data/constants.yml
dkist_processing_pac/data/py_table.txt
dkist_processing_pac/data/telescope_db.txt
dkist_processing_pac/data/CS_files/aggressive_CS.txt
dkist_processing_pac/data/CS_files/asp16_CS.txt
dkist_processing_pac/data/CS_files/efficient_CS.txt
dkist_processing_pac/data/CS_files/may_CS.txt
dkist_processing_pac/data/fit_modes/M12_fitUV.yml
dkist_processing_pac/data/fit_modes/baseline.yml
dkist_processing_pac/data/fit_modes/fit_QUV.yml
dkist_processing_pac/data/fit_modes/no_T.yml
dkist_processing_pac/data/fit_modes/use_M12.yml
dkist_processing_pac/data/fit_modes/use_M12_I_sys_per_step.yml
dkist_processing_pac/data/fit_modes/use_M12_globalRet_globalTrans.yml
dkist_processing_pac/data/init_values/OCCal_VIS_cu_pars.asdf
dkist_processing_pac/data/init_values/OCCal_VIS_tm_pars.asdf
dkist_processing_pac/fitter/__init__.py
dkist_processing_pac/fitter/fitter_parameters.py
dkist_processing_pac/fitter/fitting_core.py
dkist_processing_pac/fitter/polcal_fitter.py
dkist_processing_pac/input_data/__init__.py
dkist_processing_pac/input_data/drawer.py
dkist_processing_pac/input_data/dresser.py
dkist_processing_pac/optics/__init__.py
dkist_processing_pac/optics/calibration_unit.py
dkist_processing_pac/optics/mueller_matrices.py
dkist_processing_pac/optics/telescope.py
dkist_processing_pac/tests/__init__.py
dkist_processing_pac/tests/conftest.py
dkist_processing_pac/tests/test_calibration_unit.py
dkist_processing_pac/tests/test_drawer.py
dkist_processing_pac/tests/test_dresser.py
dkist_processing_pac/tests/test_fitter_parameters.py
dkist_processing_pac/tests/test_mueller_matrices.py
dkist_processing_pac/tests/test_nd_parameter_array.py
dkist_processing_pac/tests/test_polcal_fitter.py
dkist_processing_pac/tests/test_telescope.py
docs/Makefile
docs/background.rst
docs/changelog.rst
docs/conf.py
docs/index.rst
docs/landing_page.rst
docs/layout.rst
docs/make.bat
dkist_processing_pac-3.1.1.dist-info/METADATA
dkist_processing_pac-3.1.1.dist-info/WHEEL
dkist_processing_pac-3.1.1.dist-info/top_level.txt
dkist_processing_pac-3.1.1.dist-info/RECORD
