Metadata-Version: 2.1
Name: dkist-processing-pac
Version: 3.1.1
Summary: Modules to determine telescope polarization parameters and compute instrument demodulation matrices at DKIST
Author-email: NSO / AURA <dkistdc@nso.edu>
License: BSD-3-Clause
Project-URL: Homepage, https://nso.edu/dkist/data-center/
Project-URL: Repository, https://bitbucket.org/dkistdc/dkist-processing-pac/
Project-URL: Documentation, https://docs.dkist.nso.edu/projects/pac
Project-URL: Help, https://nso.atlassian.net/servicedesk/customer/portal/5
Classifier: Programming Language :: Python
Classifier: Programming Language :: Python :: 3
Classifier: Programming Language :: Python :: 3.11
Requires-Python: >=3.11
Requires-Dist: numpy>=1.21.0
Requires-Dist: astropy
Requires-Dist: lmfit
Requires-Dist: sunpy
Requires-Dist: scipy
Requires-Dist: pyyaml
Requires-Dist: asdf
Provides-Extra: test
Requires-Dist: pytest; extra == "test"
Requires-Dist: pytest-cov; extra == "test"
Requires-Dist: pytest-xdist; extra == "test"
Requires-Dist: towncrier; extra == "test"
Requires-Dist: dkist-data-simulator>=1.2.4; extra == "test"
Requires-Dist: dkist-header-validator>=2.0.11; extra == "test"
Requires-Dist: dkist-processing-common>=2.3.0; extra == "test"
Provides-Extra: docs
Requires-Dist: sphinx; extra == "docs"
Requires-Dist: sphinx-astropy; extra == "docs"
Requires-Dist: sphinx-changelog; extra == "docs"
Requires-Dist: sphinx-autoapi; extra == "docs"
Requires-Dist: pytest; extra == "docs"
Requires-Dist: towncrier; extra == "docs"
Requires-Dist: dkist-sphinx-theme; extra == "docs"
